fairreckitlib/__init__.py
fairreckitlib/recommender_system.py
fairreckitlib/core/__init__.py
fairreckitlib/core/core_constants.py
fairreckitlib/core/config/__init__.py
fairreckitlib/core/config/config_base_param.py
fairreckitlib/core/config/config_factories.py
fairreckitlib/core/config/config_object.py
fairreckitlib/core/config/config_option_param.py
fairreckitlib/core/config/config_parameters.py
fairreckitlib/core/config/config_value_param.py
fairreckitlib/core/config/config_yml.py
fairreckitlib/core/events/__init__.py
fairreckitlib/core/events/event_args.py
fairreckitlib/core/events/event_dispatcher.py
fairreckitlib/core/events/event_error.py
fairreckitlib/core/io/__init__.py
fairreckitlib/core/io/event_io.py
fairreckitlib/core/io/io_create.py
fairreckitlib/core/io/io_delete.py
fairreckitlib/core/io/io_utility.py
fairreckitlib/core/parsing/__init__.py
fairreckitlib/core/parsing/parse_assert.py
fairreckitlib/core/parsing/parse_config_object.py
fairreckitlib/core/parsing/parse_config_params.py
fairreckitlib/core/parsing/parse_event.py
fairreckitlib/core/pipeline/__init__.py
fairreckitlib/core/pipeline/core_pipeline.py
fairreckitlib/core/threading/__init__.py
fairreckitlib/core/threading/thread_base.py
fairreckitlib/core/threading/thread_processor.py
fairreckitlib/data/__init__.py
fairreckitlib/data/data_factory.py
fairreckitlib/data/data_modifier.py
fairreckitlib/data/data_transition.py
fairreckitlib/data/filter/__init__.py
fairreckitlib/data/filter/base_filter.py
fairreckitlib/data/filter/categorical_filter.py
fairreckitlib/data/filter/count_filter.py
fairreckitlib/data/filter/filter_config.py
fairreckitlib/data/filter/filter_config_parsing.py
fairreckitlib/data/filter/filter_constants.py
fairreckitlib/data/filter/filter_event.py
fairreckitlib/data/filter/filter_factory.py
fairreckitlib/data/filter/filter_params.py
fairreckitlib/data/filter/filter_passes.py
fairreckitlib/data/filter/numerical_filter.py
fairreckitlib/data/pipeline/__init__.py
fairreckitlib-1.0.1.dist-info/LICENSE
fairreckitlib-1.0.1.dist-info/METADATA
fairreckitlib-1.0.1.dist-info/WHEEL
fairreckitlib-1.0.1.dist-info/top_level.txt
fairreckitlib-1.0.1.dist-info/RECORD
