Metadata-Version: 2.2
Name: fairreckitlib
Version: 1.0.1
Summary: Library for FairRecKit application
Home-page: https://github.com/FairRecKit/FairRecKitLib
Author: RecCoons
Project-URL: Bug Tracker, https://github.com/FairRecKit/FairRecKitLib/issues
Classifier: Programming Language :: Python :: 3
Classifier: License :: OSI Approved :: Apache Software License
Classifier: Operating System :: OS Independent
Requires-Python: >=3.6
License-File: LICENSE
Requires-Dist: lenskit
Requires-Dist: implicit
Requires-Dist: Cython
Requires-Dist: h5py
Requires-Dist: pandas
Requires-Dist: PyYAML
Requires-Dist: scikit-surprise
Requires-Dist: rexmex
